pgpack_dumper/__init__.py
pgpack_dumper/dumper.py
pgpack_dumper/version.py
pgpack_dumper/common/__init__.py
pgpack_dumper/common/columns.py
pgpack_dumper/common/connector.py
pgpack_dumper/common/copy.py
pgpack_dumper/common/diagram.py
pgpack_dumper/common/errors.py
pgpack_dumper/common/logger.py
pgpack_dumper/common/metadata.py
pgpack_dumper/common/query.py
pgpack_dumper/common/reader.cpython-312-x86_64-linux-gnu.so
pgpack_dumper/common/reader.pxd
pgpack_dumper/common/reader.pyi
pgpack_dumper/common/reader.pyx
pgpack_dumper/common/stream.py
pgpack_dumper/common/structs.py
pgpack_dumper/common/queryes/attributes.sql
pgpack_dumper/common/queryes/copy_from.sql
pgpack_dumper/common/queryes/copy_to.sql
pgpack_dumper/common/queryes/dbname.sql
pgpack_dumper/common/queryes/gpversion.sql
pgpack_dumper/common/queryes/prepare.sql
pgpack_dumper/common/queryes/relkind.sql
pgpack_dumper-0.3.5.2.dist-info/METADATA
pgpack_dumper-0.3.5.2.dist-info/WHEEL
pgpack_dumper-0.3.5.2.dist-info/top_level.txt
pgpack_dumper-0.3.5.2.dist-info/RECORD
pgpack_dumper-0.3.5.2.dist-info/licenses/CHANGELOG.md
pgpack_dumper-0.3.5.2.dist-info/licenses/README.md
