Metadata-Version: 2.4
Name: pgpack_dumper
Version: 0.3.5.2
Summary: Library for read and write PGPack format between PostgreSQL and file.
Author-email: 0xMihalich <bayanmobile87@gmail.com>
License: MIT License
Project-URL: Homepage, https://github.com/0xMihalich/pgpack_dumper
Project-URL: Documentation, https://0xmihalich.github.io/dbhose_airflow/classes/pgpack_dumper/index.html
Project-URL: Repository, https://github.com/0xMihalich/pgpack_dumper
Project-URL: Changelog, https://github.com/0xMihalich/pgpack_dumper/blob/main/CHANGELOG.md
Classifier: Development Status :: 4 - Beta
Classifier: Intended Audience :: Developers
Classifier: Programming Language :: Python :: 3.10
Classifier: Programming Language :: Python :: 3.11
Classifier: Programming Language :: Python :: 3.12
Classifier: Programming Language :: Python :: 3.13
Classifier: Programming Language :: Python :: 3.14
Requires-Python: >=3.10
License-File: README.md
License-File: CHANGELOG.md
Requires-Dist: pgpack==0.3.2.3
Requires-Dist: psycopg_binary>=3.3.2
Requires-Dist: psycopg>=3.3.2
Requires-Dist: sqlparse>=0.5.5
Dynamic: license-file
